Workbook

Sheet ReadMe
A1: AI Cost Volatility: Build vs Buy Analysis
A3: IMPORTANT: This is an educational model to illustrate AI cost volatility concepts.
A4: Defaults are illustrative only. Customize all blue cells with your actual data.
A6: Purpose:
A7: Show how AI inference costs make traditional build-vs-buy TCO analysis unreliable.
A9: The Four Options:
A10: 1. Traditional SaaS - Predictable per-seat costs
A11: 2. Traditional Build - High upfront, low ongoing
A12: 3. SaaS + AI - Per-seat PLUS variable inference
A13: 4. Build + AI - High upfront PLUS variable inference
A15: How to Use:
A16: 1. Edit BLUE cells in Assumptions sheet
... A40: AI options: Still Volatile

Sheet Assumptions
A1: ASSUMPTIONS (Edit Blue Cells)
A3: BASIC SETTINGS
A4: Number of users/seats | C4: 1000
A5: Seat growth per year | C5: 0.1
A8: AI INFERENCE PARAMETERS (Most Important!)
A10: Monthly AI interactions | B10: Queries, tickets, chats | C10: 75000
A11: Tokens per interaction (avg) | B11: 2-5K typical | C11: 3000
A12: Cost per 1M tokens | B12: $3-15 range | C12: 4
A14: AI usage growth per year | B14: 15-50% typical | C14: 0.3
A16: Input/output token ratio | B16: Typical: 70% input, 30% output | C16: 0.7
A17: Output token cost multiplier | B17: Usually 3-5x input cost | C17: 4
A19: Usage multiplier scenario | B19: Try 1x, 5x, 10x | C19: 5
A22: CALCULATED AI INFERENCE COST (with input/output blend)
A23: Blended cost per 1M tokens: | C23: =C12*(C16+(1-C16)*C17) -> 7.6
A24: Base annual inference cost: | C24: =C10*12*C11*C23/1000000 -> 20520
A25: Year 1 with growth + multiplier: | C25: =C24*(1+C14)*C19 -> 133380
A26: Year 3 with growth + multiplier: | C26: =C24*((1+C14)^3)*C19 -> 225412.2
A29: NOTE: These defaults assume a mid-market scenario (1,000 users).
B30: Trad SaaS | C30: Trad Build | D30: SaaS + AI | E30: Build + AI
A31: Integration or build | B31: 60000 | C31: 350000 | D31: 80000 | E31: 450000
A32: Initial Testing | B32: 20000 | C32: 100000 | D32: 100000 | E32: 200000
A35: ANNUAL RECURRING COSTS
B36: Trad SaaS | C36: Trad Build | D36: SaaS + AI | E36: Build + AI
A37: Subscriptions (per seat) | B37: 1050000 | C37: 0 | D37: 1100000 | E37: 0
A38: Maintenance/Support/ML Team | B38: 0 | C38: 1100000 | D38: 0 | E38: 1300000
A39: Compliance & Audits | B39: 90000 | C39: 150000 | D39: 150000 | E39: 175000
A40: AI Inference (from above) | B40: 0 | C40: 0 | D40: =C24 -> 20520 | E40: =C24 -> 20520
A41: AI Monitoring/Testing | B41: 0 | C41: 0 | D41: 75000 | E41: 75000
A42: AI Data Storage/Processing | B42: 0 | C42: 0 | D42: 25000 | E42: 40000
A43: Model Fine-tuning | B43: 0 | C43: 0 | D43: 15000 | E43: 15000

Sheet Model
A1: 3-YEAR TOTAL COST OF OWNERSHIP
A3: Key Parameters
A4: Seats: | B4: =Assumptions!C4 -> 1000 | D4: Monthly interactions: | E4: =Assumptions!C10 -> 75000
A5: Seat growth: | B5: =Assumptions!C5 -> 0.1 | D5: Tokens/interaction: | E5: =Assumptions!C11 -> 3000
A6: AI usage growth: | B6: =Assumptions!C14 -> 0.3 | D6: Cost per 1M tokens: | E6: =Assumptions!C12 -> 4
A7: Usage multiplier: | B7: =Assumptions!C19&"x" -> 5x
A10: GROWTH FACTORS
B11: Year 1 | C11: Year 2 | D11: Year 3
A12: Seat Factor | B12: =(1+Assumptions!C5)^1 -> 1.1 | C12: =(1+Assumptions!C5)^2 -> 1.21 | D12: =(1+Assumptions!C5)^3 -> 1.331
A13: AI Usage Factor | B13: =(1+Assumptions!C14)^1*Assumptions!C19 -> 6.5 | C13: =(1+Assumptions!C14)^2*Assumptions!C19 -> 8.45 | D13: =(1+Assumptions!C14)^3*Assumptions!C19 -> 10.985
A16: ANNUAL COSTS BY YEAR
B17: Year 1 | C17: Year 2 | D17: Year 3
A18: Traditional SaaS | B18: =SUM(Assumptions!B37:B43)*B12 -> 1254000 | C18: =SUM(Assumptions!B37:B43)*C12 -> 1379400 | D18: =SUM(Assumptions!B37:B43)*D12 -> 1517340
A19: Traditional Build | B19: =SUM(Assumptions!C37:C43) -> 1250000 | C19: =SUM(Assumptions!C37:C43) -> 1250000 | D19: =SUM(Assumptions!C37:C43) -> 1250000
A20: SaaS + AI | B20: =(Assumptions!D37+Assumptions!D39)*B12 + (Assumptions!D40+Assumptions!D41+Assumptions!D42+Assumptions!D43)*B13 -> 2255880 | C20: =(Assumptions!D37+Assumptions!D39)*C12 + (Assumptions!D40+Assumptions!D41+Assumptions!D42+Assumptions!D43)*C13 -> 2657644 | D20: =(Assumptions!D37+Assumptions!D39)*D12 + (Assumptions!D40+Assumptions!D41+Assumptions!D42+Assumptions!D43)*D13 -> 3152437.2
A21: Build + AI | B21: =(Assumptions!E38+Assumptions!E39) + (Assumptions!E40+Assumptions!E41+Assumptions!E42+Assumptions!E43)*B13 -> 2453380 | C21: =(Assumptions!E38+Assumptions!E39) + (Assumptions!E40+Assumptions!E41+Assumptions!E42+Assumptions!E43)*C13 -> 2746894 | D21: =(Assumptions!E38+Assumptions!E39) + (Assumptions!E40+Assumptions!E41+Assumptions!E42+Assumptions!E43)*D13 -> 3128462.2
A24: 3-YEAR TOTAL COST (Including Upfront)
B25: Upfront | C25: Year 1-3 Total | D25: 3-Year TCO
A26: Traditional SaaS | B26: =SUM(Assumptions!B31:B32) -> 80000 | C26: =B18+C18+D18 -> 4150740 | D26: =B26+C26 -> 4230740
A27: Traditional Build | B27: =SUM(Assumptions!C31:C32) -> 450000 | C27: =B19+C19+D19 -> 3750000 | D27: =B27+C27 -> 4200000
A28: SaaS + AI | B28: =SUM(Assumptions!D31:D32) -> 180000 | C28: =B20+C20+D20 -> 8065961.2 | D28: =B28+C28 -> 8245961.2
A29: Build + AI | B29: =SUM(Assumptions!E31:E32) -> 650000 | C29: =B21+C21+D21 -> 8328736.2 | D29: =B29+C29 -> 8978736.2
A32: AI COST BREAKDOWN (Year 3)
A33: SaaS + AI: | B33: Seat costs: | C33: =(Assumptions!D37+Assumptions!D39)*D12 -> 1663750
B34: AI costs: | C34: =(Assumptions!D40+Assumptions!D41+Assumptions!D42+Assumptions!D43)*D13 -> 1488687.2
B35: AI % of total: | C35: =C34/(C33+C34) -> 0.47223374
A37: Build + AI: | B37: Fixed costs: | C37: =Assumptions!E38+Assumptions!E39 -> 1475000
B38: AI costs: | C38: =(Assumptions!E40+Assumptions!E41+Assumptions!E42+Assumptions!E43)*D13 -> 1653462.2
B39: AI % of total: | C39: =C38/(C37+C38) -> 0.52852235

Sheet Charts
A1: VISUAL COMPARISON
A3: 3-Year Total Cost Comparison
A23: Annual Cost Growth Over Time
A43: Key Observations:
A44: • Traditional options show steady, predictable growth
A45: • AI-enhanced options show accelerating growth
A46: • The gap widens each year due to AI inference scaling
A47: • Change the usage multiplier to see dramatic cost swings

Sheet Documentation
A1: HOW THIS MODEL WORKS
A4: The AI Cost Problem
A6: Traditional software costs scale predictably with seats (users).
A7: AI software costs scale unpredictably with USAGE (interactions × tokens).
A9: The Core Formula
A11: AI Inference Cost = (Monthly Interactions × 12) × Tokens × Blended Price / 1,000,000
A13: Blended Price accounts for input/output token cost difference:
A14: Blended = InputPrice × (InputRatio + OutputRatio × Multiplier)
A15: Example: $4 × (70% + 30% × 4) = $7.60 per 1M tokens
A17: Example with defaults:
A18: 75,000/month × 12 × 3,000 tokens × $7.60/1M / 1,000,000
A19: = $20,520 per year BASE cost
... A129: 5. Consider benefits (productivity) not just costs
